CIoT_Course/__init__.py
CIoT_Course/api.py
CIoT_Course-0.0.1.dist-info/LICENSE
CIoT_Course-0.0.1.dist-info/METADATA
CIoT_Course-0.0.1.dist-info/WHEEL
CIoT_Course-0.0.1.dist-info/top_level.txt
CIoT_Course-0.0.1.dist-info/RECORD
