Metadata-Version: 2.1
Name: CIoT-Course
Version: 0.0.1
Summary: Provides API for simulated stock trading platform
Home-page: https://github.com/felixweiss1999/CIoT_Course
Author: Felix Weiss
Author-email: felixweiss1999@gmail.com
Classifier: Programming Language :: Python :: 3
Classifier: License :: OSI Approved :: MIT License
Classifier: Operating System :: OS Independent
Requires-Python: >=3.6
License-File: LICENSE
